speakdata/__about__.py
speakdata/__init__.py
speakdata/__main__.py
speakdata/speakdata.py
speakdata-1.0.0.dist-info/LICENSE
speakdata-1.0.0.dist-info/METADATA
speakdata-1.0.0.dist-info/WHEEL
speakdata-1.0.0.dist-info/entry_points.txt
speakdata-1.0.0.dist-info/top_level.txt
speakdata-1.0.0.dist-info/RECORD
