Metadata-Version: 2.1
Name: speakdata
Version: 1.0.0
Summary: How to pronounce binary data
Home-page: https://github.com/tyehle/speakdata
Author: Tobin Yehle
Author-email: tobinyehle@gmail.com
License: MIT
Platform: UNKNOWN
Classifier: Development Status :: 4 - Beta
Classifier: License :: OSI Approved :: MIT License
Classifier: Programming Language :: Python :: 3
Classifier: Programming Language :: Python :: 3.6
Classifier: Programming Language :: Python :: 3.7
Classifier: Programming Language :: Python :: 3.8
Classifier: Operating System :: OS Independent
Classifier: Environment :: Console
Classifier: Typing :: Typed
